million_verifier/MillionVerifier.py
million_verifier/__init__.py
million_verifier/enums/MVError.py
million_verifier/enums/MVStatus.py
million_verifier/enums/__init__.py
million_verifier/exceptions/__init__.py
million_verifier/exceptions/exceptions.py
million_verifier/responses/MVFileResponse.py
million_verifier/responses/MVGetFileResponse.py
million_verifier/responses/MVResponse.py
million_verifier/responses/MVUploadFileResponse.py
million_verifier/responses/MVVerifyResponse.py
million_verifier/responses/__init__.py
mine_lead/MineLead.py
mine_lead/__init__.py
mine_lead/enums/MLSearchStatus.py
mine_lead/enums/__init__.py
mine_lead/exceptions/__init__.py
mine_lead/exceptions/exceptions.py
mine_lead/responses/MLResponse.py
mine_lead/responses/MLSearchEmailResponse.py
mine_lead/responses/MLSearchResponse.py
mine_lead/responses/__init__.py
mine_lead-1.1.dist-info/METADATA
mine_lead-1.1.dist-info/WHEEL
mine_lead-1.1.dist-info/top_level.txt
mine_lead-1.1.dist-info/RECORD
